azure/servicefabric/__init__.py
azure/servicefabric/_configuration.py
azure/servicefabric/_service_fabric_client_ap_is.py
azure/servicefabric/version.py
azure/servicefabric/models/__init__.py
azure/servicefabric/models/_models.py
azure/servicefabric/models/_models_py3.py
azure/servicefabric/models/_service_fabric_client_ap_is_enums.py
azure/servicefabric/operations/__init__.py
azure/servicefabric/operations/_mesh_application_operations.py
azure/servicefabric/operations/_mesh_code_package_operations.py
azure/servicefabric/operations/_mesh_gateway_operations.py
azure/servicefabric/operations/_mesh_network_operations.py
azure/servicefabric/operations/_mesh_secret_operations.py
azure/servicefabric/operations/_mesh_secret_value_operations.py
azure/servicefabric/operations/_mesh_service_operations.py
azure/servicefabric/operations/_mesh_service_replica_operations.py
azure/servicefabric/operations/_mesh_volume_operations.py
azure/servicefabric/operations/_service_fabric_client_ap_is_operations.py
azure_servicefabric-8.2.0.0.dist-info/METADATA
azure_servicefabric-8.2.0.0.dist-info/WHEEL
azure_servicefabric-8.2.0.0.dist-info/top_level.txt
azure_servicefabric-8.2.0.0.dist-info/RECORD
