Metadata-Version: 2.1
Name: azure-servicefabric
Version: 8.2.0.0
Summary: Microsoft Azure Service Fabric Client Library for Python
Home-page: https://github.com/Azure/azure-sdk-for-python
Author: Microsoft Corporation
Author-email: azpysdkhelp@microsoft.com
License: MIT License
Platform: UNKNOWN
Classifier: Development Status :: 5 - Production/Stable
Classifier: Programming Language :: Python
Classifier: Programming Language :: Python :: 2
Classifier: Programming Language :: Python :: 2.7
Classifier: Programming Language :: Python :: 3
Classifier: Programming Language :: Python :: 3.5
Classifier: Programming Language :: Python :: 3.6
Classifier: Programming Language :: Python :: 3.7
Classifier: Programming Language :: Python :: 3.8
Classifier: Programming Language :: Python :: 3.9
Classifier: License :: OSI Approved :: MIT License
Requires-Dist: msrest (>=0.6.21)
Requires-Dist: azure-common (~=1.1)
Requires-Dist: azure-nspkg ; python_version<'3.0'
